trollbufr/__init__.py
trollbufr/bufr.py
trollbufr/bufr_main.py
trollbufr/load_file.py
trollbufr/tester.py
trollbufr/update.py
trollbufr/version.py
trollbufr/coder/__init__.py
trollbufr/coder/bdata.py
trollbufr/coder/bufr_sect.py
trollbufr/coder/bufr_types.py
trollbufr/coder/errors.py
trollbufr/coder/functions.py
trollbufr/coder/load_tables.py
trollbufr/coder/operator.py
trollbufr/coder/parse_bufrdc.py
trollbufr/coder/parse_eccodes.py
trollbufr/coder/parse_libdwd.py
trollbufr/coder/subset.py
trollbufr/coder/tables.py
trollbufr-0.6.1.dist-info/DESCRIPTION.rst
trollbufr-0.6.1.dist-info/METADATA
trollbufr-0.6.1.dist-info/RECORD
trollbufr-0.6.1.dist-info/WHEEL
trollbufr-0.6.1.dist-info/entry_points.txt
trollbufr-0.6.1.dist-info/metadata.json
trollbufr-0.6.1.dist-info/top_level.txt
