Metadata-Version: 2.0
Name: trollbufr
Version: 0.6.1
Summary: Reading meteorological data format BUFR in pure Python
Home-page: UNKNOWN
Author: Alexander Maul
Author-email: alexander.maul@dwd.de
License: UNKNOWN
Platform: UNKNOWN
Classifier: Development Status :: 4 - Beta
Classifier: Intended Audience :: Science/Research
Classifier: License :: OSI Approved :: GNU Lesser General Public License v3 or later (LGPLv3+)
Classifier: Operating System :: OS Independent
Classifier: Programming Language :: Python :: 2
Classifier: Programming Language :: Python :: 2.6
Classifier: Programming Language :: Python :: 2.7
Classifier: Topic :: Scientific/Engineering
Requires-Python: >=2.6, <3
Requires-Dist: bitstring
